pynats2/__init__.py
pynats2/client.py
pynats2/exceptions.py
pynats2/nuid.py
pynats2-0.9.0.dist-info/AUTHORS
pynats2-0.9.0.dist-info/LICENSE
pynats2-0.9.0.dist-info/METADATA
pynats2-0.9.0.dist-info/WHEEL
pynats2-0.9.0.dist-info/pbr.json
pynats2-0.9.0.dist-info/top_level.txt
pynats2-0.9.0.dist-info/RECORD
