Metadata-Version: 2.1
Name: pynats2
Version: 0.9.0
Summary: 'Thread based NATS client for Python 3',
Home-page: https://github.com/yosshy/pynats2
Author: Akira Yoshiyama
Author-email: akirayoshiyama@gmail.com
License: MIT
Keywords: nats,message bus
Platform: UNKNOWN
Classifier: Development Status :: 4 - Beta
Classifier: Environment :: Console
Classifier: Environment :: OpenStack
Classifier: Intended Audience :: Developers
Classifier: Intended Audience :: Information Technology
Classifier: License :: OSI Approved :: MIT License
Classifier: Operating System :: OS Independent
Classifier: Programming Language :: Python
Classifier: Programming Language :: Python :: 3
Classifier: Programming Language :: Python :: 3.6
Classifier: Programming Language :: Python :: 3.7
Requires-Dist: pbr
Requires-Dist: dataclasses ; (python_version<'3.7')
